setup.py
shinkenplugins/__init__.py
shinkenplugins.plugins.ski_stations.egg-info/PKG-INFO
shinkenplugins.plugins.ski_stations.egg-info/SOURCES.txt
shinkenplugins.plugins.ski_stations.egg-info/dependency_links.txt
shinkenplugins.plugins.ski_stations.egg-info/entry_points.txt
shinkenplugins.plugins.ski_stations.egg-info/namespace_packages.txt
shinkenplugins.plugins.ski_stations.egg-info/requires.txt
shinkenplugins.plugins.ski_stations.egg-info/top_level.txt
shinkenplugins/plugins/__init__.py
shinkenplugins/plugins/ski_stations/__init__.py
shinkenplugins/plugins/ski_stations/essai_lxml.py
shinkenplugins/plugins/ski_stations/ski_stations.py