Metadata-Version: 1.0
Name: shinkenplugins.plugins.ski-stations
Version: 1.2
Summary: Check Ski Stations traffic
Home-page: https://github.com/savoirfairelinux/sfl-shinken-plugins
Author: Grégory Starck
Author-email: gregory.starck@savoirfairelinux.com
License: GPL3+
Platform: any
